prodready
