Metadata-Version: 1.0
Name: django-production-ready
Version: 0.0.3a0
Summary: A Django app that runs simple tests to check if your app is production ready.
Home-page: http://github.com/agiliq/django-production-ready
Author: Agiliq Solutions
Author-email: hello@agiliq.com
License: BSD
Platform: UNKNOWN
Classifier: Development Status :: 3 - Alpha
Classifier: Environment :: Web Environment
Classifier: Intended Audience :: Developers
Classifier: License :: OSI Approved :: BSD License
Classifier: Operating System :: OS Independent
Classifier: Programming Language :: Python
Classifier: Framework :: Django
